censore/__init__.py
censore/profanity_filter.py
censore/data/exclude_patterns/en.txt
censore/data/exclude_patterns/ru.txt
censore/data/exclude_patterns/uk.txt
censore/data/patterns/en.txt
censore/data/patterns/ru.txt
censore/data/patterns/uk.txt
tests/__init__.py
tests/test.py
censore-0.2.1.dist-info/LICENSE
censore-0.2.1.dist-info/METADATA
censore-0.2.1.dist-info/WHEEL
censore-0.2.1.dist-info/top_level.txt
censore-0.2.1.dist-info/RECORD
