Metadata-Version: 2.1
Name: censore
Version: 0.2.1
Summary: A package for censoring profanity in text
Home-page: https://github.com/censor-text/censore
Author: Okinea Dev
Classifier: Programming Language :: Python :: 3
Classifier: License :: OSI Approved :: MIT License
Classifier: Operating System :: OS Independent
Requires-Python: >=3.6
License-File: LICENSE
